{
    "en": {
        "nav_play": "Play",
        "nav_library": "Library",
        "nav_settings": "Settings",

        "play_empty_title": "No track selected",
        "play_empty_sub": "Please load a MIDI file from the library",
        "play_tuning": "Tuning",
        "play_jitter": "Rhythm Jitter",
        "play_jitter_desc": "Simulates slight beat instability. Higher values feel more 'amateur'.",
        "play_stagger": "Chord Stagger",
        "play_stagger_desc": "Forces simultaneous notes to slightly offset, preventing loud bursts.",
        "play_hesitation": "Hesitation",
        "play_hesitation_desc": "Pause time between key presses. Smaller values can reduce delay during fast play, but too small may cause keys to not trigger properly. Recommended to set at least 0.016s (frame time of 60 FPS).",
        "play_hesitation_min": "Hesitation Min",
        "play_hesitation_min_desc": "Minimum pause between key press (seconds).",
        "play_hesitation_max": "Hesitation Max",
        "play_hesitation_max_desc": "Maximum pause between key press (seconds).",
        "play_keybinds": "Keybinds",
        "play_key_ctrl": "Octave down",
        "play_key_shift": "Octave Up",
        "play_key_down": "3 Octaves Down",
        "play_key_up": "3 Octaves Up",
        "play_progress_label": "Progress",
        "play_mode_label": "Mode",
        "play_split_toggle": "Enable split playback",
        "play_split_label": "Channels",
        "play_channel_label": "Channel {}",
        "play_channel_short_label": "Ch {}",
        "play_class_drum": "Drum",
        "play_class_bass": "Bass",
        "play_class_guitar": "Guitar",
        "play_class_keys": "Keys",
        "play_class_unknown": "Unknown",
        "play_mode_normal": "Normal",
        "play_mode_repeat_one": "Repeat One",
        "play_mode_repeat_all": "Repeat All",
        "play_role_keyboard": "Keyboard",
        "play_role_bass": "Bass",
        "play_role_guitar": "Guitar",
        "play_role_drum": "Drum",
        "play_prev": "Previous track",
        "play_next": "Next track",
        "play_prev_unavailable": "Already at first track",
        "play_next_unavailable": "Already at last track",

        "lib_title": "My Library",
        "lib_search": "Search tracks...",
        "lib_import": "Import MIDI",
        "lib_select_all": "Select All",
        "lib_invert_selection": "Invert Selection",
        "lib_remove_selected": "Remove Selected",

        "set_title": "Preferences",
        "set_lang": "Interface Language",
        "set_lang_sub": "Change the display language",
        "set_dark": "Dark Mode",
        "set_smart_split": "Enable smart track split",
        "set_hotkey": "Emergency Stop Hotkey: ESC/Backspace",
        "set_version": "Version: StarResonanceMidi {}",
        "set_project_meta": "GitHub: https://github.com/etanolo/StarResonanceMidi | License: AGPL-3.0 | Based on Flet",

        "msg_stopping_playlist": "Stopping playlist...",
        "msg_import_at_least_one": "Please import at least one MIDI file first",
        "msg_thread_still_running": "Playback thread is still running, please wait",
        "msg_track_finished_next": "Track {} finished, next track starts in {:.1f}s",
        "msg_switch_to_game": "Playback starts in {:.1f}s. Switch to the game window now.",
        "msg_playlist_stopped": "Playlist stopped",
        "msg_hotkey_stopped": "Emergency stop",
        "msg_playlist_completed": "Playlist completed",
        "msg_hotkey_unavailable": "Global emergency stop is unavailable. Grant Accessibility permission on macOS.",
        "msg_pick_midi_dialog": "Select MIDI files (multi-select)",
        "msg_read_path_failed": "Cannot read selected file path",
        "msg_playlist_count": "{} tracks total",
        "msg_imported_count": "Imported {} MIDI files",
        "msg_removed_count": "Removed {} track(s) from playlist",
        "msg_remove_select_at_least_one": "Please select at least one track to remove",
        "msg_engine_error": "Engine error: {}",
        "msg_track_split_ready": "Track split analysis ready (confidence: {:.0%}).",
        "msg_track_split_ready_count": "Detected {} channel(s) for split.",
        "msg_track_split_disabled_no_channel": "No playable channel detected for split.",
        "msg_track_split_disabled": "Track split disabled for this MIDI: {}",
        "msg_track_split_reason_ok": "structured",
        "msg_track_split_reason_no_tracks": "no valid playable tracks detected",
        "msg_track_split_reason_low_confidence": "low confidence",
        "msg_track_split_reason_ambiguous": "ambiguous role scores",
        "msg_track_split_reason_high_conflict": "high multi-instrument conflict",
        "msg_split_enabled": "Split playback enabled.",
        "msg_split_disabled": "Split playback disabled.",
        "msg_smart_split_enabled": "Smart track split enabled.",
        "msg_smart_split_disabled": "Smart track split disabled.",
        "msg_split_role_keep_one": "At least one channel must stay enabled."
    },
    "ja": {
        "nav_play": "再生",
        "nav_library": "ライブラリ",
        "nav_settings": "設定",

        "play_empty_title": "曲が選択されていません",
        "play_empty_sub": "ライブラリからMIDIファイルを読み込んでください",
        "play_tuning": "調整",
        "play_jitter": "Rhythm Jitter",
        "play_jitter_desc": "演奏時のわずかなズレをシミュレートします。数値が大きいほど「素人感」が出ます。",
        "play_stagger": "Chord Stagger",
        "play_stagger_desc": "同時に押される音符をわずかにずらし、音の重なりによる爆音を防ぎます。",
        "play_hesitation": "間隔設定",
        "play_hesitation_desc": "キー入力間の待機時間。小さすぎるとキーが正しく反応しない可能性があります。0.016秒（60FPSのフレーム時間）以上を推奨します。",
        "play_hesitation_min": "間隔 最小",
        "play_hesitation_min_desc": "キー入力間の最小待機時間（秒）。",
        "play_hesitation_max": "間隔 最大",
        "play_hesitation_max_desc": "キー入力間の最大待機時間（秒）。",
        "play_keybinds": "キー設定",
        "play_key_ctrl": "オクターブ下",
        "play_key_shift": "オクターブ上",
        "play_key_down": "3オクターブ下",
        "play_key_up": "3オクターブ上",
        "play_progress_label": "進行",
        "play_mode_label": "再生モード",
        "play_split_toggle": "分離再生を有効化",
        "play_split_label": "チャンネル",
        "play_channel_label": "チャンネル {}",
        "play_channel_short_label": "Ch {}",
        "play_class_drum": "ドラム",
        "play_class_bass": "ベース",
        "play_class_guitar": "ギター",
        "play_class_keys": "鍵盤",
        "play_class_unknown": "不明",
        "play_mode_normal": "通常再生",
        "play_mode_repeat_one": "単曲ループ",
        "play_mode_repeat_all": "リストループ",
        "play_role_keyboard": "キーボード",
        "play_role_bass": "ベース",
        "play_role_guitar": "ギター",
        "play_role_drum": "ドラム",
        "play_prev": "前の曲",
        "play_next": "次の曲",
        "play_prev_unavailable": "先頭の曲です",
        "play_next_unavailable": "最後の曲です",

        "lib_title": "マイライブラリ",
        "lib_search": "曲を検索...",
        "lib_import": "MIDIを追加",
        "lib_select_all": "全選択",
        "lib_invert_selection": "選択反転",
        "lib_remove_selected": "選択をリストから削除",

        "set_title": "環境設定",
        "set_lang": "表示言語",
        "set_lang_sub": "Change the display language",
        "set_dark": "ダークモード",
        "set_smart_split": "スマート分離を有効化",
        "set_hotkey": "緊急停止ホットキー：ESC/Backspace",
        "set_version": "バージョン情報: StarResonanceMidi {}",
        "set_project_meta": "GitHub: https://github.com/etanolo/StarResonanceMidi | ライセンス: AGPL-3.0 | Flet ベース",

        "msg_stopping_playlist": "プレイリストを停止しています...",
        "msg_import_at_least_one": "先にMIDIファイルを1曲以上読み込んでください",
        "msg_thread_still_running": "再生スレッドがまだ動作中です。しばらくお待ちください",
        "msg_track_finished_next": "{}曲目が終了しました。{:.1f}秒後に次の曲を再生します",
        "msg_switch_to_game": "{:.1f}秒後に再生開始します。今すぐゲーム画面に切り替えてください。",
        "msg_playlist_stopped": "プレイリストを停止しました",
        "msg_hotkey_stopped": "緊急停止しました",
        "msg_playlist_completed": "プレイリストの再生が完了しました",
        "msg_hotkey_unavailable": "グローバル緊急停止を利用できません。macOS でアクセシビリティ権限を付与してください。",
        "msg_pick_midi_dialog": "MIDIファイルを選択（複数選択可）",
        "msg_read_path_failed": "選択したファイルのパスを読み取れません",
        "msg_playlist_count": "全{}曲",
        "msg_imported_count": "{}曲のMIDIを読み込みました",
        "msg_removed_count": "プレイリストから{}曲を削除しました",
        "msg_remove_select_at_least_one": "削除する曲を1つ以上選択してください",
        "msg_engine_error": "エンジンエラー: {}",
        "msg_track_split_ready": "トラック分離解析の準備完了（信頼度: {:.0%}）。",
        "msg_track_split_ready_count": "分離対象チャンネルを{}件検出しました。",
        "msg_track_split_disabled_no_channel": "分離可能なチャンネルが見つかりませんでした。",
        "msg_track_split_disabled": "このMIDIではトラック分離を無効化しました: {}",
        "msg_track_split_reason_ok": "構造は良好です",
        "msg_track_split_reason_no_tracks": "再生可能な有効トラックが見つかりません",
        "msg_track_split_reason_low_confidence": "信頼度が低すぎます",
        "msg_track_split_reason_ambiguous": "判定スコアが曖昧です",
        "msg_track_split_reason_high_conflict": "複数楽器の衝突が大きすぎます",
        "msg_split_enabled": "分離再生を有効にしました。",
        "msg_split_disabled": "分離再生を無効にしました。",
        "msg_smart_split_enabled": "スマート分離を有効にしました。",
        "msg_smart_split_disabled": "スマート分離を無効にしました。",
        "msg_split_role_keep_one": "少なくとも1つのチャンネルを有効にしてください。"
    },
    "zh": {
        "nav_play": "播放",
        "nav_library": "曲库",
        "nav_settings": "设置",

        "play_empty_title": "当前未选择曲目",
        "play_empty_sub": "请从曲库加载 MIDI 文件",
        "play_tuning": "微调",
        "play_jitter": "Rhythm Jitter",
        "play_jitter_desc": "模拟真实弹奏时微小的节拍不稳。数值越大，节奏越具“业余感”。",
        "play_stagger": "Chord Stagger",
        "play_stagger_desc": "将同时按下的多个音符强制微小错开。这能增加流水感并极大防止多音叠爆。",
        "play_hesitation": "按键间隔设置",
        "play_hesitation_desc": "按键之间的停顿时间。较小的数值可以消除快速演奏时的延迟感，过小的数值可能导致按键无法正确触发。推荐至少设置为 0.016 秒（60帧的帧时间）。",
        "play_hesitation_min": "按键间隔最小值",
        "play_hesitation_min_desc": "按键输入间的最小停顿时间（秒）。",
        "play_hesitation_max": "按键间隔最大值",
        "play_hesitation_max_desc": "按键输入间的最大停顿时间（秒）。",
        "play_keybinds": "按键绑定",
        "play_key_ctrl": "低八度",
        "play_key_shift": "高八度",
        "play_key_down": "低3个八度",
        "play_key_up": "高3个八度",
        "play_progress_label": "播放进度",
        "play_mode_label": "播放模式",
        "play_split_toggle": "启用分轨播放",
        "play_split_label": "通道",
        "play_channel_label": "通道 {}",
        "play_channel_short_label": "Ch {}",
        "play_class_drum": "鼓",
        "play_class_bass": "贝斯",
        "play_class_guitar": "吉他",
        "play_class_keys": "键盘",
        "play_class_unknown": "未知",
        "play_mode_normal": "顺序播放",
        "play_mode_repeat_one": "单曲循环",
        "play_mode_repeat_all": "列表循环",
        "play_role_keyboard": "键盘",
        "play_role_bass": "贝斯",
        "play_role_guitar": "吉他",
        "play_role_drum": "鼓",
        "play_prev": "上一曲",
        "play_next": "下一曲",
        "play_prev_unavailable": "已是第一首",
        "play_next_unavailable": "已是最后一首",

        "lib_title": "我的曲库",
        "lib_search": "搜索曲目...",
        "lib_import": "导入 MIDI",
        "lib_select_all": "全选",
        "lib_invert_selection": "反选",
        "lib_remove_selected": "移除已选",

        "set_title": "软件设置",
        "set_lang": "界面语言",
        "set_lang_sub": "Change the display language",
        "set_dark": "深色模式",
        "set_smart_split": "启用智能分轨",
        "set_hotkey": "紧急停止热键：ESC/退格",
        "set_version": "版本信息: StarResonanceMidi {}",
        "set_project_meta": "GitHub: https://github.com/etanolo/StarResonanceMidi | 协议: AGPL-3.0 | 基于 Flet",

        "msg_stopping_playlist": "正在停止播放列表...",
        "msg_import_at_least_one": "请先导入至少一首 MIDI 文件",
        "msg_thread_still_running": "播放线程仍在运行，请稍候",
        "msg_track_finished_next": "第 {} 首结束，{:.1f} 秒后播放下一首",
        "msg_switch_to_game": "{:.1f} 秒后开始演奏，请立刻切到游戏窗口。",
        "msg_playlist_stopped": "播放列表已停止",
        "msg_hotkey_stopped": "紧急停止",
        "msg_playlist_completed": "播放列表已完成",
        "msg_hotkey_unavailable": "全局紧急停止不可用。请在 macOS 中授予辅助功能权限。",
        "msg_pick_midi_dialog": "选择 MIDI 文件（可多选）",
        "msg_read_path_failed": "无法读取所选文件路径",
        "msg_playlist_count": "共 {} 首",
        "msg_imported_count": "已导入 {} 首 MIDI",
        "msg_removed_count": "已从播放列表移除 {} 首",
        "msg_remove_select_at_least_one": "请至少选择一首要移除的曲目",
        "msg_engine_error": "引擎错误：{}",
        "msg_track_split_ready": "分轨分析就绪（置信度：{:.0%}）。",
        "msg_track_split_ready_count": "已检测到 {} 个可分轨通道。",
        "msg_track_split_disabled_no_channel": "未检测到可分轨的可播放通道。",
        "msg_track_split_disabled": "该 MIDI 已禁用分轨：{}",
        "msg_track_split_reason_ok": "结构良好",
        "msg_track_split_reason_no_tracks": "未检测到可播放的有效音轨",
        "msg_track_split_reason_low_confidence": "置信度过低",
        "msg_track_split_reason_ambiguous": "分类分数过于接近",
        "msg_track_split_reason_high_conflict": "多乐器冲突过高",
        "msg_split_enabled": "已启用分轨播放。",
        "msg_split_disabled": "已关闭分轨播放。",
        "msg_smart_split_enabled": "已启用智能分轨。",
        "msg_smart_split_disabled": "已关闭智能分轨。",
        "msg_split_role_keep_one": "至少保留一个通道为启用状态。"
    }
}